{
  "Oklahoma": 570.3,
  "Ohio State": 535.6,
  "Clemson": 527.2,
  "Memphis": 523.1,
  "UCF": 522.7,
  "Alabama": 522,
  "Houston": 512.5,
  "West Virginia": 512.3,
  "Ole Miss": 510.5,
  "Oklahoma State": 500.2,
  "Utah State": 497.4,
  "Texas Tech": 485.2,
  "Missouri": 481.8,
  "Florida Atlantic": 478.8,
  "Texas A&M": 471.6,
  "Ohio": 466.8,
  "Arkansas State": 466.2,
  "Georgia": 464.9,
  "Syracuse": 464.8,
  "North Texas": 460.5,
  "Boise State": 459.5,
  "Baylor": 459.1,
  "Cincinnati": 458.5,
  "Arizona": 457.7,
  "Nebraska": 456.2,
  "NC State": 456.1,
  "Washington State": 451.5,
  "Wake Forest": 449.8,
  "Purdue": 443.9,
  "Toledo": 443.8,
  "North Carolina": 442.1,
  "Notre Dame": 440.1,
  "South Florida": 437.7,
  "UMass": 437.6,
  "Western Michigan": 436.8,
  "Wisconsin": 431.1,
  "Appalachian State": 431,
  "Nevada": 430.8,
  "Virginia Tech": 428.2,
  "Old Dominion": 427.8,
  "Oregon": 427.2,
  "Florida": 426.7,
  "South Carolina": 425.6,
  "Louisiana": 424.3,
  "Penn State": 423,
  "Florida International": 421.5,
  "Fresno State": 421.5,
  "Hawai'i": 419.9,
  "Michigan": 419.5,
  "Arizona State": 416.7,
  "Indiana": 415.2,
  "Air Force": 414.8,
  "Louisiana Monroe": 414.8,
  "Washington": 414.6,
  "Buffalo": 414.5,
  "East Carolina": 414.4,
  "Texas": 411.3,
  "Vanderbilt": 411.2,
  "Colorado State": 410.5,
  "Temple": 409.5,
  "Georgia Tech": 408.8,
  "Illinois": 408.7,
  "Ball State": 408.6,
  "UAB": 405.7,
  "Duke": 405.7,
  "Oregon State": 404.8,
  "Boston College": 404.3,
  "LSU": 402.1,
  "Tulane": 401.1,
  "Mississippi State": 397.4,
  "Utah": 395.8,
  "Marshall": 393.6,
  "Middle Tennessee": 393.4,
  "UCLA": 392.6,
  "Colorado": 392.6,
  "Army": 392.5,
  "UNLV": 391.2,
  "Auburn": 389.9,
  "Troy": 389.4,
  "SMU": 387.2,
  "Virginia": 384.8,
  "Kent State": 383.6,
  "USC": 382.6,
  "Louisiana Tech": 382.1,
  "Stanford": 381,
  "Minnesota": 379.6,
  "Coastal Carolina": 379.3,
  "Connecticut": 378.4,
  "Georgia State": 378.2,
  "Tulsa": 377.6,
  "Iowa": 375,
  "Eastern Michigan": 372.1,
  "Miami (OH)": 372,
  "Maryland": 371.4,
  "Iowa State": 371,
  "New Mexico State": 370.5,
  "Pittsburgh": 369.7,
  "TCU": 368.1,
  "Southern Mississippi": 367.6,
  "BYU": 364.9,
  "Western Kentucky": 363.7,
  "Florida State": 361.2,
  "Kentucky": 360.8,
  "Miami": 358.8,
  "South Alabama": 355.3,
  "Bowling Green": 355.3,
  "Northwestern": 354.4,
  "Louisville": 352.6,
  "Kansas": 350.8,
  "Navy": 348.9,
  "San Diego State": 348.8,
  "Georgia Southern": 345.2,
  "Kansas State": 344.7,
  "California": 343.5,
  "Charlotte": 343.1,
  "Michigan State": 342.1,
  "Arkansas": 335.7,
  "Wyoming": 330.8,
  "New Mexico": 330.4,
  "Texas State": 330.3,
  "Tennessee": 325.5,
  "San José State": 323.7,
  "Northern Illinois": 322.3,
  "Rice": 318.4,
  "UTEP": 307.7,
  "Akron": 294.4,
  "Rutgers": 266.3,
  "Central Michigan": 254.7,
  "UT San Antonio": 247.1,
  "Liberty": 422.9
}
