{
  "Florida Atlantic": 22,
  "Oregon": 20,
  "Clemson": 19,
  "San Diego State": 18,
  "Alabama": 17,
  "Louisiana Tech": 17,
  "Baylor": 17,
  "LSU": 17,
  "San José State": 16,
  "TCU": 16,
  "Florida": 16,
  "Cincinnati": 16,
  "Tennessee": 15,
  "Ball State": 15,
  "Ohio State": 15,
  "BYU": 15,
  "Minnesota": 14,
  "Texas Tech": 14,
  "North Carolina": 14,
  "Wake Forest": 14,
  "Utah": 14,
  "Virginia Tech": 14,
  "Appalachian State": 14,
  "Hawai'i": 14,
  "Syracuse": 13,
  "Western Michigan": 13,
  "UCF": 13,
  "Central Michigan": 13,
  "Washington": 13,
  "Arizona State": 13,
  "South Florida": 12,
  "Navy": 12,
  "Illinois": 12,
  "Florida International": 12,
  "Liberty": 12,
  "Michigan State": 12,
  "South Carolina": 12,
  "Virginia": 12,
  "Wisconsin": 12,
  "Iowa": 12,
  "Tulane": 12,
  "Oklahoma State": 12,
  "Arkansas State": 12,
  "Wyoming": 12,
  "Texas": 12,
  "Coastal Carolina": 11,
  "Kansas State": 11,
  "Buffalo": 11,
  "Western Kentucky": 11,
  "Nebraska": 11,
  "East Carolina": 11,
  "Eastern Michigan": 11,
  "Troy": 11,
  "Utah State": 11,
  "Colorado": 11,
  "Nevada": 11,
  "Memphis": 11,
  "Arizona": 11,
  "Fresno State": 11,
  "Miami (OH)": 11,
  "UMass": 10,
  "Louisiana Monroe": 10,
  "Southern Mississippi": 10,
  "Mississippi State": 10,
  "Miami": 10,
  "Washington State": 10,
  "Maryland": 10,
  "Louisiana": 10,
  "Marshall": 10,
  "Texas A&M": 10,
  "Ole Miss": 10,
  "Penn State": 10,
  "Auburn": 10,
  "Boston College": 10,
  "Boise State": 10,
  "Charlotte": 9,
  "Old Dominion": 9,
  "South Alabama": 9,
  "Michigan": 9,
  "Duke": 9,
  "Georgia State": 9,
  "Notre Dame": 9,
  "Purdue": 9,
  "Georgia Southern": 9,
  "UNLV": 9,
  "Pittsburgh": 9,
  "USC": 9,
  "SMU": 9,
  "Missouri": 8,
  "Kentucky": 8,
  "West Virginia": 8,
  "Houston": 8,
  "Stanford": 8,
  "Middle Tennessee": 8,
  "Oregon State": 8,
  "Temple": 8,
  "California": 8,
  "Georgia": 8,
  "Florida State": 8,
  "Bowling Green": 7,
  "Texas State": 7,
  "Army": 7,
  "Georgia Tech": 7,
  "Connecticut": 7,
  "Kent State": 7,
  "Northwestern": 7,
  "Air Force": 7,
  "Toledo": 7,
  "Indiana": 7,
  "Louisville": 7,
  "UAB": 7,
  "Oklahoma": 7,
  "Colorado State": 6,
  "Vanderbilt": 6,
  "UT San Antonio": 6,
  "Arkansas": 6,
  "Rutgers": 6,
  "Rice": 6,
  "Kansas": 6,
  "Iowa State": 6,
  "Akron": 5,
  "UTEP": 5,
  "Tulsa": 5,
  "New Mexico State": 5,
  "UCLA": 5,
  "Ohio": 5,
  "Northern Illinois": 4,
  "North Texas": 4,
  "NC State": 4,
  "New Mexico": 4
}
